qgoferutils/__init__.py
qgoferutils/_modidx.py
qgoferutils/config.py
qgoferutils/core.py
qgoferutils/db.py
qgoferutils/logger.py
qgoferutils/manage_index.py
qgoferutils/requests.py
qgoferutils-0.0.8.dist-info/LICENSE
qgoferutils-0.0.8.dist-info/METADATA
qgoferutils-0.0.8.dist-info/WHEEL
qgoferutils-0.0.8.dist-info/entry_points.txt
qgoferutils-0.0.8.dist-info/top_level.txt
qgoferutils-0.0.8.dist-info/RECORD
